{
  "ok": true,
  "status": "ready",
  "scannedAt": "2026-06-28T10:04:36.851Z",
  "refreshMs": 900000,
  "transport": "macmini-ha-collector",
  "sourceStatus": {
    "baseline": "ready",
    "ha": "live",
    "coolkit": "not_included"
  },
  "energyUsage": {
    "source": "HA local collector snapshot, refreshed 2026-06-28T10:04:36.851Z",
    "periods": {
      "today": 9.468,
      "week": null,
      "month": 302.353,
      "year": null
    }
  },
  "devices": [
    {
      "protocol": "Wi-Fi",
      "name": "Aqara P3 Plug",
      "model": "Aqara P3 Plug / Xiaomi Miot",
      "sortKwh": 302.353,
      "sortMode": "month kWh",
      "watts": 0.94,
      "facts": [
        [
          "Power",
          "0.94 W"
        ],
        [
          "Today",
          "9.468 kWh"
        ],
        [
          "Month",
          "302.353 kWh"
        ]
      ],
      "externalSource": "aqara-p3"
    },
    {
      "protocol": "Matter",
      "name": "Computer desk S60TPF",
      "model": "SONOFF S60TPF",
      "sortKwh": 14.99,
      "sortMode": "meter kWh",
      "watts": 91.53,
      "facts": [
        [
          "Total",
          "14.99 kWh"
        ],
        [
          "Power",
          "91.53 W"
        ],
        [
          "Current",
          "0.54 A"
        ]
      ],
      "externalSource": "desk-s60tpf"
    },
    {
      "protocol": "Matter",
      "name": "Electric kettle SONOFF WS01TPE Outlet",
      "model": "SONOFF WS01TPE",
      "sortKwh": 9.31,
      "sortMode": "meter kWh",
      "watts": 0,
      "facts": [
        [
          "Total",
          "9.31 kWh"
        ],
        [
          "Power",
          "0.00 W"
        ],
        [
          "Voltage",
          "236.54 V"
        ]
      ],
      "externalSource": "kettle-ws01tpe"
    },
    {
      "protocol": "Wi-Fi",
      "name": "Shelly Plug S Gen3",
      "model": "Shelly Plug S Gen3",
      "sortKwh": 1.93905,
      "sortMode": "meter kWh",
      "watts": 2.1,
      "facts": [
        [
          "Returned",
          "0 kWh"
        ],
        [
          "Power",
          "2.1 W"
        ],
        [
          "Total",
          "1.939 kWh"
        ]
      ],
      "externalSource": "shelly-plug-s-gen3"
    },
    {
      "protocol": "Wi-Fi",
      "name": "Kitchen Shelly Pro 3EM",
      "model": "Shelly Pro 3EM",
      "sortKwh": 59.32097,
      "sortMode": "circuit kWh",
      "watts": 149.216,
      "facts": [
        [
          "Returned",
          "0.043 kWh"
        ],
        [
          "Power",
          "149.2 W"
        ],
        [
          "Total",
          "59.321 kWh"
        ]
      ],
      "externalSource": "kitchen-shelly-pro-3em"
    },
    {
      "protocol": "Matter",
      "name": "Bathroom hair dryer SONOFF WS01TPF",
      "model": "SONOFF WS01TPF",
      "sortKwh": 0.98,
      "sortMode": "meter kWh",
      "watts": 0,
      "facts": [
        [
          "Total",
          "0.98 kWh"
        ],
        [
          "Power",
          "0.00 W"
        ],
        [
          "Voltage",
          "235.74 V"
        ]
      ],
      "externalSource": "bathroom-ws01tpf"
    },
    {
      "protocol": "Wi-Fi",
      "name": "IamMeter Incomer",
      "model": "IAMMETER / local API",
      "sortKwh": 424.963,
      "sortMode": "import kWh",
      "watts": 249,
      "facts": [
        [
          "Current",
          "1.55 A"
        ],
        [
          "Voltage",
          "238.7 V"
        ],
        [
          "Export",
          "2.83 kWh"
        ],
        [
          "Power",
          "249 W"
        ]
      ],
      "externalSource": "iammeter-incomer"
    }
  ]
}
